kfai_env/__init__.py
kfai_env/_version.py
kfai_env/env.py
kfai_env/test/__init__.py
kfai_env/test/test_env.py
kungfuai_env-0.2.3.dist-info/LICENSE
kungfuai_env-0.2.3.dist-info/METADATA
kungfuai_env-0.2.3.dist-info/WHEEL
kungfuai_env-0.2.3.dist-info/top_level.txt
kungfuai_env-0.2.3.dist-info/RECORD
