Metadata-Version: 2.1
Name: kungfuai-env
Version: 0.2.3
Summary: Environment handling to simplify development environments
Home-page: https://github.com/kungfuai/env
Author: Endurance Idehen
Author-email: endurance.idehen@kungfu.ai
License: MIT
Platform: UNKNOWN
Classifier: License :: OSI Approved :: MIT License
Classifier: Programming Language :: Python :: 3
Classifier: Programming Language :: Python :: 3.8
Requires-Dist: python-dotenv
